{"lands":{"autotiles":[],"floors":[{"k":[64,0,0,16,0],"v":{"t":[2,9]}},{"k":[64,0,0,19,0],"v":{"t":[2,12]}},{"k":[65,0,0,18,0],"v":{"t":[3,11]}},{"k":[66,0,0,17,0],"v":{"t":[4,10]}},{"k":[67,0,0,16,0],"v":{"t":[5,9]}},{"k":[65,0,0,19,0],"v":{"t":[3,12]}},{"k":[66,0,0,18,0],"v":{"t":[4,11]}},{"k":[67,0,0,17,0],"v":{"t":[5,10]}},{"k":[68,0,0,16,0],"v":{"t":[6,9]}},{"k":[64,0,0,20,0],"v":{"t":[53,0]}},{"k":[64,0,0,17,0],"v":{"t":[2,10]}},{"k":[65,0,0,16,0],"v":{"t":[3,9]}},{"k":[64,0,0,18,0],"v":{"t":[2,11]}},{"k":[65,0,0,17,0],"v":{"t":[3,10]}},{"k":[66,0,0,16,0],"v":{"t":[4,9]}},{"k":[68,0,0,19,0],"v":{"t":[6,12]}},{"k":[69,0,0,18,0],"v":{"t":[7,11]}},{"k":[70,0,0,17,0],"v":{"t":[8,10]}},{"k":[71,0,0,16,0],"v":{"t":[9,9]}},{"k":[64,0,0,23,0],"v":{"t":[53,3]}},{"k":[65,0,0,22,0],"v":{"t":[54,2]}},{"k":[66,0,0,21,0],"v":{"t":[55,1]}},{"k":[67,0,0,20,0],"v":{"t":[56,0]}},{"k":[69,0,0,19,0],"v":{"t":[7,12]}},{"k":[70,0,0,18,0],"v":{"t":[8,11]}},{"k":[71,0,0,17,0],"v":{"t":[9,10]}},{"k":[72,0,0,16,0],"v":{"t":[10,9]}},{"k":[64,0,0,24,0],"v":{"t":[53,4]}},{"k":[65,0,0,23,0],"v":{"t":[54,3]}},{"k":[66,0,0,22,0],"v":{"t":[55,2]}},{"k":[67,0,0,21,0],"v":{"t":[56,1]}},{"k":[68,0,0,20,0],"v":{"t":[57,0]}},{"k":[66,0,0,19,0],"v":{"t":[4,12]}},{"k":[67,0,0,18,0],"v":{"t":[5,11]}},{"k":[68,0,0,17,0],"v":{"t":[6,10]}},{"k":[69,0,0,16,0],"v":{"t":[7,9]}},{"k":[64,0,0,21,0],"v":{"t":[53,1]}},{"k":[65,0,0,20,0],"v":{"t":[54,0]}},{"k":[67,0,0,19,0],"v":{"t":[5,12]}},{"k":[68,0,0,18,0],"v":{"t":[6,11]}},{"k":[69,0,0,17,0],"v":{"t":[7,10]}},{"k":[70,0,0,16,0],"v":{"t":[8,9]}},{"k":[64,0,0,22,0],"v":{"t":[53,2]}},{"k":[65,0,0,21,0],"v":{"t":[54,1]}},{"k":[66,0,0,20,0],"v":{"t":[55,0]}},{"k":[71,0,0,20,0],"v":{"t":[9,13]}},{"k":[72,0,0,19,0],"v":{"t":[10,12]}},{"k":[73,0,0,18,0],"v":{"t":[11,11]}},{"k":[74,0,0,17,0],"v":{"t":[12,10]}},{"k":[64,0,0,27,0],"v":{"t":[53,7]}},{"k":[65,0,0,26,0],"v":{"t":[54,6]}},{"k":[66,0,0,25,0],"v":{"t":[55,5]}},{"k":[67,0,0,24,0],"v":{"t":[56,4]}},{"k":[68,0,0,23,0],"v":{"t":[57,3]}},{"k":[69,0,0,22,0],"v":{"t":[58,2]}},{"k":[70,0,0,21,0],"v":{"t":[59,1]}},{"k":[75,0,0,16,0],"v":{"t":[0,1]}},{"k":[71,0,0,21,0],"v":{"t":[9,14]}},{"k":[72,0,0,20,0],"v":{"t":[10,13]}},{"k":[73,0,0,19,0],"v":{"t":[11,12]}},{"k":[74,0,0,18,0],"v":{"t":[12,11]}},{"k":[64,0,0,28,0],"v":{"t":[53,8]}},{"k":[65,0,0,27,0],"v":{"t":[54,7]}},{"k":[66,0,0,26,0],"v":{"t":[55,6]}},{"k":[67,0,0,25,0],"v":{"t":[56,5]}},{"k":[68,0,0,24,0],"v":{"t":[57,4]}},{"k":[69,0,0,23,0],"v":{"t":[58,3]}},{"k":[70,0,0,22,0],"v":{"t":[59,2]}},{"k":[75,0,0,17,0],"v":{"t":[0,2]}},{"k":[76,0,0,16,0],"v":{"t":[1,1]}},{"k":[70,0,0,19,0],"v":{"t":[8,12]}},{"k":[71,0,0,18,0],"v":{"t":[9,11]}},{"k":[72,0,0,17,0],"v":{"t":[10,10]}},{"k":[73,0,0,16,0],"v":{"t":[11,9]}},{"k":[64,0,0,25,0],"v":{"t":[53,5]}},{"k":[65,0,0,24,0],"v":{"t":[54,4]}},{"k":[66,0,0,23,0],"v":{"t":[55,3]}},{"k":[67,0,0,22,0],"v":{"t":[56,2]}},{"k":[68,0,0,21,0],"v":{"t":[57,1]}},{"k":[69,0,0,20,0],"v":{"t":[58,0]}},{"k":[71,0,0,19,0],"v":{"t":[9,12]}},{"k":[72,0,0,18,0],"v":{"t":[10,11]}},{"k":[73,0,0,17,0],"v":{"t":[11,10]}},{"k":[74,0,0,16,0],"v":{"t":[12,9]}},{"k":[64,0,0,26,0],"v":{"t":[53,6]}},{"k":[65,0,0,25,0],"v":{"t":[54,5]}},{"k":[66,0,0,24,0],"v":{"t":[55,4]}},{"k":[67,0,0,23,0],"v":{"t":[56,3]}},{"k":[68,0,0,22,0],"v":{"t":[57,2]}},{"k":[69,0,0,21,0],"v":{"t":[58,1]}},{"k":[70,0,0,20,0],"v":{"t":[59,0]}},{"k":[71,0,0,24,0],"v":{"t":[6,13]}},{"k":[72,0,0,23,0],"v":{"t":[7,12]}},{"k":[73,0,0,22,0],"v":{"t":[11,15]}},{"k":[74,0,0,21,0],"v":{"t":[12,14]}},{"k":[64,0,0,31,0],"v":{"t":[53,11]}},{"k":[65,0,0,30,0],"v":{"t":[54,10]}},{"k":[66,0,0,29,0],"v":{"t":[55,9]}},{"k":[67,0,0,28,0],"v":{"t":[56,8]}},{"k":[68,0,0,27,0],"v":{"t":[57,7]}},{"k":[69,0,0,26,0],"v":{"t":[58,6]}},{"k":[70,0,0,25,0],"v":{"t":[59,5]}},{"k":[75,0,0,20,0],"v":{"t":[0,5]}},{"k":[76,0,0,19,0],"v":{"t":[1,4]}},{"k":[77,0,0,18,0],"v":{"t":[2,3]}},{"k":[78,0,0,17,0],"v":{"t":[3,2]}},{"k":[79,0,0,16,0],"v":{"t":[4,1]}},{"k":[71,0,0,25,0],"v":{"t":[6,14]}},{"k":[72,0,0,24,0],"v":{"t":[7,13]}},{"k":[73,0,0,23,0],"v":{"t":[8,12]}},{"k":[74,0,0,22,0],"v":{"t":[12,15]}},{"k":[65,0,0,31,0],"v":{"t":[54,11]}},{"k":[66,0,0,30,0],"v":{"t":[55,10]}},{"k":[67,0,0,29,0],"v":{"t":[56,9]}},{"k":[68,0,0,28,0],"v":{"t":[57,8]}},{"k":[69,0,0,27,0],"v":{"t":[58,7]}},{"k":[70,0,0,26,0],"v":{"t":[59,6]}},{"k":[75,0,0,21,0],"v":{"t":[0,6]}},{"k":[76,0,0,20,0],"v":{"t":[1,5]}},{"k":[77,0,0,19,0],"v":{"t":[2,4]}},{"k":[78,0,0,18,0],"v":{"t":[3,3]}},{"k":[79,0,0,17,0],"v":{"t":[4,2]}},{"k":[71,0,0,22,0],"v":{"t":[9,15]}},{"k":[72,0,0,21,0],"v":{"t":[10,14]}},{"k":[73,0,0,20,0],"v":{"t":[11,13]}},{"k":[74,0,0,19,0],"v":{"t":[12,12]}},{"k":[64,0,0,29,0],"v":{"t":[53,9]}},{"k":[65,0,0,28,0],"v":{"t":[54,8]}},{"k":[66,0,0,27,0],"v":{"t":[55,7]}},{"k":[67,0,0,26,0],"v":{"t":[56,6]}},{"k":[68,0,0,25,0],"v":{"t":[57,5]}},{"k":[69,0,0,24,0],"v":{"t":[58,4]}},{"k":[70,0,0,23,0],"v":{"t":[59,3]}},{"k":[75,0,0,18,0],"v":{"t":[0,3]}},{"k":[76,0,0,17,0],"v":{"t":[1,2]}},{"k":[77,0,0,16,0],"v":{"t":[2,1]}},{"k":[71,0,0,23,0],"v":{"t":[6,12]}},{"k":[72,0,0,22,0],"v":{"t":[10,15]}},{"k":[73,0,0,21,0],"v":{"t":[11,14]}},{"k":[74,0,0,20,0],"v":{"t":[12,13]}},{"k":[64,0,0,30,0],"v":{"t":[53,10]}},{"k":[65,0,0,29,0],"v":{"t":[54,9]}},{"k":[66,0,0,28,0],"v":{"t":[55,8]}},{"k":[67,0,0,27,0],"v":{"t":[56,7]}},{"k":[68,0,0,26,0],"v":{"t":[57,6]}},{"k":[69,0,0,25,0],"v":{"t":[58,5]}},{"k":[70,0,0,24,0],"v":{"t":[59,4]}},{"k":[75,0,0,19,0],"v":{"t":[0,4]}},{"k":[76,0,0,18,0],"v":{"t":[1,3]}},{"k":[77,0,0,17,0],"v":{"t":[2,2]}},{"k":[78,0,0,16,0],"v":{"t":[3,1]}},{"k":[71,0,0,28,0],"v":{"t":[6,10]}},{"k":[72,0,0,27,0],"v":{"t":[7,9]}},{"k":[73,0,0,26,0],"v":{"t":[8,15]}},{"k":[74,0,0,25,0],"v":{"t":[9,14]}},{"k":[68,0,0,31,0],"v":{"t":[57,11]}},{"k":[69,0,0,30,0],"v":{"t":[58,10]}},{"k":[70,0,0,29,0],"v":{"t":[59,9]}},{"k":[75,0,0,24,0],"v":{"t":[0,9]}},{"k":[76,0,0,23,0],"v":{"t":[1,8]}},{"k":[77,0,0,22,0],"v":{"t":[2,7]}},{"k":[78,0,0,21,0],"v":{"t":[3,6]}},{"k":[79,0,0,20,0],"v":{"t":[4,5]}},{"k":[71,0,0,29,0],"v":{"t":[6,11]}},{"k":[72,0,0,28,0],"v":{"t":[7,10]}},{"k":[73,0,0,27,0],"v":{"t":[8,9]}},{"k":[74,0,0,26,0],"v":{"t":[9,15]}},{"k":[69,0,0,31,0],"v":{"t":[58,11]}},{"k":[70,0,0,30,0],"v":{"t":[59,10]}},{"k":[75,0,0,25,0],"v":{"t":[0,10]}},{"k":[76,0,0,24,0],"v":{"t":[1,9]}},{"k":[77,0,0,23,0],"v":{"t":[2,8]}},{"k":[78,0,0,22,0],"v":{"t":[3,7]}},{"k":[79,0,0,21,0],"v":{"t":[4,6]}},{"k":[71,0,0,26,0],"v":{"t":[6,15]}},{"k":[72,0,0,25,0],"v":{"t":[7,14]}},{"k":[73,0,0,24,0],"v":{"t":[8,13]}},{"k":[74,0,0,23,0],"v":{"t":[9,12]}},{"k":[66,0,0,31,0],"v":{"t":[55,11]}},{"k":[67,0,0,30,0],"v":{"t":[56,10]}},{"k":[68,0,0,29,0],"v":{"t":[57,9]}},{"k":[69,0,0,28,0],"v":{"t":[58,8]}},{"k":[70,0,0,27,0],"v":{"t":[59,7]}},{"k":[75,0,0,22,0],"v":{"t":[0,7]}},{"k":[76,0,0,21,0],"v":{"t":[1,6]}},{"k":[77,0,0,20,0],"v":{"t":[2,5]}},{"k":[78,0,0,19,0],"v":{"t":[3,4]}},{"k":[79,0,0,18,0],"v":{"t":[4,3]}},{"k":[71,0,0,27,0],"v":{"t":[6,9]}},{"k":[72,0,0,26,0],"v":{"t":[7,15]}},{"k":[73,0,0,25,0],"v":{"t":[8,14]}},{"k":[74,0,0,24,0],"v":{"t":[9,13]}},{"k":[67,0,0,31,0],"v":{"t":[56,11]}},{"k":[68,0,0,30,0],"v":{"t":[57,10]}},{"k":[69,0,0,29,0],"v":{"t":[58,9]}},{"k":[70,0,0,28,0],"v":{"t":[59,8]}},{"k":[75,0,0,23,0],"v":{"t":[0,8]}},{"k":[76,0,0,22,0],"v":{"t":[1,7]}},{"k":[77,0,0,21,0],"v":{"t":[2,6]}},{"k":[78,0,0,20,0],"v":{"t":[3,5]}},{"k":[79,0,0,19,0],"v":{"t":[4,4]}},{"k":[72,0,0,31,0],"v":{"t":[7,13]}},{"k":[73,0,0,30,0],"v":{"t":[8,12]}},{"k":[74,0,0,29,0],"v":{"t":[9,11]}},{"k":[75,0,0,28,0],"v":{"t":[0,13]}},{"k":[76,0,0,27,0],"v":{"t":[1,12]}},{"k":[77,0,0,26,0],"v":{"t":[2,11]}},{"k":[78,0,0,25,0],"v":{"t":[3,10]}},{"k":[79,0,0,24,0],"v":{"t":[4,9]}},{"k":[73,0,0,31,0],"v":{"t":[8,13]}},{"k":[74,0,0,30,0],"v":{"t":[9,12]}},{"k":[75,0,0,29,0],"v":{"t":[0,14]}},{"k":[76,0,0,28,0],"v":{"t":[1,13]}},{"k":[77,0,0,27,0],"v":{"t":[2,12]}},{"k":[78,0,0,26,0],"v":{"t":[3,11]}},{"k":[79,0,0,25,0],"v":{"t":[4,10]}},{"k":[71,0,0,30,0],"v":{"t":[6,12]}},{"k":[72,0,0,29,0],"v":{"t":[7,11]}},{"k":[73,0,0,28,0],"v":{"t":[8,10]}},{"k":[74,0,0,27,0],"v":{"t":[9,9]}},{"k":[70,0,0,31,0],"v":{"t":[59,11]}},{"k":[75,0,0,26,0],"v":{"t":[0,11]}},{"k":[76,0,0,25,0],"v":{"t":[1,10]}},{"k":[77,0,0,24,0],"v":{"t":[2,9]}},{"k":[78,0,0,23,0],"v":{"t":[3,8]}},{"k":[79,0,0,22,0],"v":{"t":[4,7]}},{"k":[71,0,0,31,0],"v":{"t":[6,13]}},{"k":[72,0,0,30,0],"v":{"t":[7,12]}},{"k":[73,0,0,29,0],"v":{"t":[8,11]}},{"k":[74,0,0,28,0],"v":{"t":[9,10]}},{"k":[75,0,0,27,0],"v":{"t":[0,12]}},{"k":[76,0,0,26,0],"v":{"t":[1,11]}},{"k":[77,0,0,25,0],"v":{"t":[2,10]}},{"k":[78,0,0,24,0],"v":{"t":[3,9]}},{"k":[79,0,0,23,0],"v":{"t":[4,8]}},{"k":[76,0,0,31,0],"v":{"t":[11,13]}},{"k":[77,0,0,30,0],"v":{"t":[2,15]}},{"k":[78,0,0,29,0],"v":{"t":[3,14]}},{"k":[79,0,0,28,0],"v":{"t":[4,13]}},{"k":[77,0,0,31,0],"v":{"t":[0,13]}},{"k":[78,0,0,30,0],"v":{"t":[3,15]}},{"k":[79,0,0,29,0],"v":{"t":[4,14]}},{"k":[74,0,0,31,0],"v":{"t":[9,13]}},{"k":[75,0,0,30,0],"v":{"t":[0,15]}},{"k":[76,0,0,29,0],"v":{"t":[1,14]}},{"k":[77,0,0,28,0],"v":{"t":[2,13]}},{"k":[78,0,0,27,0],"v":{"t":[3,12]}},{"k":[79,0,0,26,0],"v":{"t":[4,11]}},{"k":[75,0,0,31,0],"v":{"t":[10,13]}},{"k":[76,0,0,30,0],"v":{"t":[1,15]}},{"k":[77,0,0,29,0],"v":{"t":[2,14]}},{"k":[78,0,0,28,0],"v":{"t":[3,13]}},{"k":[79,0,0,27,0],"v":{"t":[4,12]}},{"k":[78,0,0,31,0],"v":{"t":[1,13]}},{"k":[79,0,0,30,0],"v":{"t":[4,15]}},{"k":[79,0,0,31,0],"v":{"t":[2,13]}}]},"moun":{"a":[],"o":[]},"objs":{"list":[]},"objs3d":{"a":[],"o":[]},"sprites":{"list":[],"overflow":[],"walls":[]}}